cytonuiautomatordump/LICENSE.txt
cytonuiautomatordump/__init__.py
cytonuiautomatordump/cyuiautomatordump.pyx
cytonuiautomatordump/cyuiautomatordump_compile.py
cytonuiautomatordump/requirements.txt
cytonuiautomatordump/thirdparty.json
cytonuiautomatordump-0.10.dist-info/LICENSE.rst
cytonuiautomatordump-0.10.dist-info/METADATA
cytonuiautomatordump-0.10.dist-info/WHEEL
cytonuiautomatordump-0.10.dist-info/top_level.txt
cytonuiautomatordump-0.10.dist-info/RECORD
