Metadata-Version: 2.1
Name: cytonuiautomatordump
Version: 0.10
Summary: uiautomator parser for Android
Home-page: https://github.com/hansalemaos/cytonuiautomatordump
Author: Johannes Fischer
Author-email: aulasparticularesdealemaosp@gmail.com
License: MIT
Keywords: Android,uiautomator
Classifier: Development Status :: 4 - Beta
Classifier: Programming Language :: Python :: 3 :: Only
Classifier: Programming Language :: Python :: 3.10
Classifier: Topic :: Software Development :: Libraries :: Python Modules
Classifier: Topic :: Utilities
License-File: LICENSE.rst
Requires-Dist: Cython
Requires-Dist: cythondfprint
Requires-Dist: cythonscreencap2ppm
Requires-Dist: exceptdrucker
Requires-Dist: numpy
Requires-Dist: pandas
Requires-Dist: setuptools
Requires-Dist: xmlhtml2pandas
